CHANGELOG.txt
LICENSE.txt
MANIFEST.in
README.md
requirements.txt
setup.cfg
setup.py
cytocad/__init__.py
cytocad/bam_coverage.c
cytocad/bam_coverage.pyx
cytocad/change_detection.py
cytocad/cytocad
cytocad/depth_limit.py
cytocad/ideogram.py
cytocad/input.py
cytocad/version.py
cytocad.egg-info/PKG-INFO
cytocad.egg-info/SOURCES.txt
cytocad.egg-info/dependency_links.txt
cytocad.egg-info/requires.txt
cytocad.egg-info/top_level.txt
cytocad/data/__init__.py
cytocad/data/hg38_curated_filter_main_arte.bed
cytocad/data/hg38_sizes_main.bed
cytocad/data/hg38_ucsc_ideogram.bed