Metadata-Version: 2.1
Name: cytocad
Version: 1.0.2
Summary: Large copy-number variation detector with low-depth whole-genome sequencing data
Home-page: https://github.com/cytham/cytocad
Author: Tham Cheng Yong
Author-email: cytham@nus.edu.sg
License: gpl-3.0
Download-URL: https://github.com/cytham/cytocad/releases
Keywords: cytocad,copy number variation,CNV,whole genome sequencing,low depth,change point detection
Platform: UNKNOWN
Classifier: Operating System :: POSIX :: Linux
Classifier: Programming Language :: Python :: 3.6
Classifier: Programming Language :: Python :: 3.7
Classifier: Programming Language :: Python :: 3.8
Classifier: License :: OSI Approved :: GNU General Public License v3 (GPLv3)
Classifier: Topic :: Scientific/Engineering :: Bio-Informatics
Requires-Python: >=3.6
